[
  {
    "GitHub repo": "Persuasion_105",
    "cover_artist": "Heather Main",
    "local_big_file": "rtc_Persuasion_Heather+Main.jpg"
  },
  {
    "GitHub repo": "Don-Quixote_996",
    "cover_artist": "Wedha Abdul Rasyid",
    "local_big_file": "rtc_Don+Quixote_Wedha+Abdul+Rasyid.jpeg"
  },
  {
    "GitHub repo": "Middlemarch_145",
    "cover_artist": "Ed Gaither - Modern Electrographic",
    "local_big_file": "rtc_Middlemarch_Ed+Gaither+-+Modern+Electrographic.jpeg"
  },
  {
    "GitHub repo": "A-Tale-of-Two-Cities_98",
    "cover_artist": "Alexis Lampley",
    "local_big_file": "rtc_A+Tale+of+Two+Cities_Alexis+Lampley.jpg"
  },
  {
    "GitHub repo": "The-Call-of-the-Wild_215",
    "cover_artist": "Michael van Kekem",
    "local_big_file": "rtc_Call+of+the+Wild_Michael+van+Kekem.jpeg"
  },
  {
    "GitHub repo": "Crime-and-Punishment_2554",
    "cover_artist": "Mario Fuentes",
    "local_big_file": "rtc_Crime+and+Punishment_Mario+Fuentes.jpeg"
  },
  {
    "GitHub repo": "The-Strange-Case-of-Dr.-Jekyll-and-Mr.-Hyde_42",
    "cover_artist": "mafMOVE",
    "local_big_file": "rtc_Dr+++Jekyll+and+Mr+++Hyde_mafMOVE.jpeg"
  },
  {
    "GitHub repo": "Dracula_345",
    "cover_artist": "Steve St. Pierre",
    "local_big_file": "rtc_Dracula_Steve+St+++Pierre.jpeg"
  },
  {
    "GitHub repo": "Flatland--A-Romance-of-Many-Dimensions--Illustrated-_201",
    "cover_artist": "alex mckeithen",
    "local_big_file": "rtc_Flatland_alex+mckeithen.jpeg"
  },
  {
    "GitHub repo": "Household-Stories-by-the-Brothers-Grimm_19068",
    "cover_artist": "Kathryn Delaney",
    "local_big_file": "rtc_Grimm+s+Fairy+Tales_Kathryn+Delaney.jpeg"
  },
  {
    "GitHub repo": "Heart-of-Darkness_219",
    "cover_artist": "Louise Norman",
    "local_big_file": "rtc_Heart+of+Darkness_Louise+Norman.jpeg"
  },
  {
    "GitHub repo": "A-Journey-into-the-Interior-of-the-Earth_3748",
    "cover_artist": "Ed Gaither - Modern Electrographic",
    "local_big_file": "rtc_Journey+to+the+Center+of+the+Earth_Ed+Gaither+-+Modern+Electrographic.jpeg"
  },
  {
    "GitHub repo": "Jude-the-Obscure_153",
    "cover_artist": "Stefano Zanardi",
    "local_big_file": "rtc_Jude+the+Obscure_Stefano+Zanardi.jpeg"
  },
  {
    "GitHub repo": "King-Solomon-s-Mines_2166",
    "cover_artist": "Ed Gaither - Modern Electrographic",
    "local_big_file": "rtc_King+Solomon+s+Mines_Ed+Gaither+-+Modern+Electrographic.jpeg"
  },
  {
    "GitHub repo": "Little-Women_514",
    "cover_artist": "Lia Marcoux",
    "local_big_file": "rtc_Little+Women_Lia+Marcoux.jpeg"
  },
  {
    "GitHub repo": "Madame-Bovary_2413",
    "cover_artist": "Alex Morris",
    "local_big_file": "rtc_Madame+Bovary_Alex+Morris.jpg"
  },
  {
    "GitHub repo": "The-Life-and-Adventures-of-Robinson-Crusoe_521",
    "cover_artist": "J.D. Reeves",
    "local_big_file": "rtc_Robinson+Crusoe_J++D+++Reeves.jpeg"
  },
  {
    "GitHub repo": "The-Awakening-and-Selected-Short-Stories_160",
    "cover_artist": "Ed Gaither - Modern Electrographic",
    "local_big_file": "rtc_The+Awakening_Ed+Gaither+-+Modern+Electrographic.jpeg"
  },
  {
    "GitHub repo": "The-Jungle_140",
    "cover_artist": "Wade Greenberg",
    "local_big_file": "rtc_The+Jungle_Wade+Greenberg.jpeg"
  },
  {
    "GitHub repo": "The-Jungle-Book_236",
    "cover_artist": "Jeff Walters",
    "local_big_file": "rtc_The+Jungle+Book_Jeff+Walters.jpeg"
  },
  {
    "GitHub repo": "Metamorphosis_5200",
    "cover_artist": "Frank Myles",
    "local_big_file": "rtc_The+Metamorphosis_Frank+Myles.jpeg"
  },
  {
    "GitHub repo": "The-Picture-of-Dorian-Gray_174",
    "cover_artist": "Maelle Doliveux",
    "local_big_file": "rtc_Picture+of+Dorian+Gray_Maelle+Doliveux.jpeg"
  },
  {
    "GitHub repo": "The-Red-Badge-of-Courage_73",
    "cover_artist": "Ed Gaither - Modern Electrographic",
    "local_big_file": "rtc_Red+Badge+Of+Courage_Ed+Gaither+-+Modern+Electrographic.jpg"
  },
  {
    "GitHub repo": "The-Scarlet-Letter_33",
    "cover_artist": "MrFurious",
    "local_big_file": "rtc_The+Scarlet+Letter_MrFurious.jpeg"
  },
  {
    "GitHub repo": "The-War-of-the-Worlds_36",
    "cover_artist": "Kjell Roger Ringstad",
    "local_big_file": "rtc_War+of+the+Worlds_Kjell+Roger+Ringstad.jpeg"
  },
  {
    "GitHub repo": "The-Wonderful-Wizard-of-Oz_55",
    "cover_artist": "David Hays",
    "local_big_file": "rtc_The+Wonderful+Wizard+of+Oz_David+Hays.jpeg"
  },
  {
    "GitHub repo": "This-Side-of-Paradise_805",
    "cover_artist": "Sawsan",
    "local_big_file": "rtc_This+Side+of+Paradise_Sawsan.jpeg"
  },
  {
    "GitHub repo": "Anna-Karenina_1399",
    "cover_artist": "Victoria Fernandez",
    "local_big_file": "rtc_Anna+Karenina_Victoria+Fernandez.jpeg"
  },
  {
    "GitHub repo": "Divine-Comedy-Longfellow-s-Translation-Hell_1001",
    "cover_artist": null,
    "local_big_file": null
  },
  {
    "GitHub repo": "Swann-s-Way_7178",
    "cover_artist": "Louise Norman",
    "local_big_file": "rtc_Swann+s+Way_Louise+Norman.jpeg"
  },
  {
    "GitHub repo": "The-Hunchback-of-Notre-Dame_6539",
    "cover_artist": "Christopher Komuro",
    "local_big_file": "rtc_The+Hunchback+of+Notre+Dame_Christopher+Komuro.jpeg"
  },
  {
    "GitHub repo": "The-Three-Musketeers_1257",
    "cover_artist": "Ioannis Fetanis",
    "local_big_file": "rtc_Three+Musketeers_Ioannis+Fetanis.jpeg"
  },
  {
    "GitHub repo": "Through-the-Looking-Glass_12",
    "cover_artist": "Alex Kostiw",
    "local_big_file": "rtc_Through+the+Looking+Glass_Alex+Kostiw.jpeg"
  },
  {
    "GitHub repo": "Winesburg-Ohio--A-Group-of-Tales-of-Ohio-Small-Town-Life_416",
    "cover_artist": "Hanna Norris",
    "local_big_file": "rtc_Winesburg,+Ohio_Hanna+Norris.jpeg"
  },
  {
    "GitHub repo": "My-Antonia_242",
    "cover_artist": "Ed Gaither - Modern Electrographic",
    "local_big_file": "rtc_My+Antonia_Ed+Gaither+-+Modern+Electrographic.jpeg"
  },
  {
    "GitHub repo": "Bleak-House_1023",
    "cover_artist": "Ed Gaither - Modern Electrographic",
    "local_big_file": "rtc_Bleak+House_Ed+Gaither+-+Modern+Electrographic.jpeg"
  },
  {
    "GitHub repo": "Twenty-Thousand-Leagues-under-the-Sea_164",
    "cover_artist": "Wade Greenberg",
    "local_big_file": "rtc_Twenty+Thousand+Leagues+Under+the+Sea_Wade+Greenberg.jpeg"
  },
  {
    "GitHub repo": "Jane-Eyre_1260",
    "cover_artist": "Ed Gaither - Modern Electrographic",
    "local_big_file": "rtc_Jane+Eyre_Ed+Gaither+-+Modern+Electrographic.jpg"
  },
  {
    "GitHub repo": "Moby-Dick--Or-The-Whale_2701",
    "cover_artist": "Black Dwarf Designs",
    "local_big_file": "rtc_Moby+Dick_Black+Dwarf+Designs.jpg"
  },
  {
    "GitHub repo": "Narrative-of-the-Life-of-Frederick-Douglass-an-American-Slave_23",
    "cover_artist": "Benjy Brooke",
    "local_big_file": "rtc_Narrative+of+the+Life+of+Frederick+Douglass_Benjy+Brooke.jpeg"
  },
  {
    "GitHub repo": "Pride-and-Prejudice_1342",
    "cover_artist": "Tim Daniel",
    "local_big_file": "rtc_Pride+and+Prejudice_Tim+Daniel.jpeg"
  },
  {
    "GitHub repo": "The-Adventures-of-Sherlock-Holmes_1661",
    "cover_artist": "Maria Papaefstathiou",
    "local_big_file": "rtc_The+Adventures+of+Sherlock+Holmes_Maria+Papaefstathiou.jpeg"
  },
  {
    "GitHub repo": "The-Brothers-Karamazov_28054",
    "cover_artist": "Roberlan Borges",
    "local_big_file": "rtc_The+Brothers+Karamazov_Roberlan+Borges.jpeg"
  },
  {
    "GitHub repo": "Frankenstein_84",
    "cover_artist": "Luis Prado",
    "local_big_file": "rtc_Frankenstein_Luis+Prado.jpeg"
  },
  {
    "GitHub repo": "Dubliners_2814",
    "cover_artist": "Devin",
    "local_big_file": "rtc_Dubliners_Devin.jpeg"
  },
  {
    "GitHub repo": "Adventures-of-Huckleberry-Finn_76",
    "cover_artist": "Priscilla Parizeau",
    "local_big_file": "rtc_The+Adventures+of+Huckleberry+Finn_Priscilla+Parizeau.jpeg"
  },
  {
    "GitHub repo": "The-Time-Machine_35",
    "cover_artist": "Jon Cain",
    "local_big_file": "rtc_The+Time+Machine_Jon+Cain.jpeg"
  },
  {
    "GitHub repo": "",
    "cover_artist": "nick fairbank - f9 design",
    "local_big_file": "rtc_Ulysses_nick+fairbank+-+f9+design.jpeg"
  },
  {
    "GitHub repo": "Gulliver-s-Travels_829",
    "cover_artist": "Naomi Sloman",
    "local_big_file": "rtc_Gulliver+s+Travels_Naomi+Sloman.jpeg"
  },
  {
    "GitHub repo": "Les-Mis-rables_135",
    "cover_artist": "Jon Cain",
    "local_big_file": "rtc_Les+Miserables_Jon+Cain.jpeg"
  },
  {
    "GitHub repo": "The-Count-of-Monte-Cristo_1184",
    "cover_artist": "Sara Nauman",
    "local_big_file": "rtc_The+Count+of+Monte+Cristo_Sara+Nauman.jpeg"
  },
  {
    "GitHub repo": "The-Works-of-Edgar-Allan-Poe-The-Raven-EditionTable-Of-Contents-And-Index-Of-The-Five-Volumes_25525",
    "cover_artist": "Adam S. Doyle",
    "local_big_file": "rtc_The+Works+of+Edgar+Allan+Poe_Adam+S+++Doyle.jpeg"
  },
  {
    "GitHub repo": "War-and-Peace_2600",
    "cover_artist": "T.M. Serlin",
    "local_big_file": "rtc_War+and+Peace_T++M+++Serlin.jpeg"
  }
]